pynetix/__init__.py
pynetix/__main__.py
pynetix/app.py
pynetix/maintab.py
pynetix/mainwindow.py
pynetix/lib/__init__.py
pynetix/lib/data.py
pynetix/other/__init__.py
pynetix/other/colours.py
pynetix/other/icons.py
pynetix/other/lib.py
pynetix/other/logging.py
pynetix/other/stylesheet.py
pynetix/other/worker.py
pynetix/resources/default_settings.ini
pynetix/resources/colourschemes/default.json
pynetix/resources/icons/raw/down_arrow.svg
pynetix/resources/icons/raw/right_arrow.svg
pynetix/resources/stylesheets/application.qss
pynetix/resources/stylesheets/sidebar.qss
pynetix/resources/stylesheets/splitter_base.qss
pynetix/resources/stylesheets/splitter_hover.qss
pynetix/widgets/__init__.py
pynetix/widgets/filetreewidget.py
pynetix/widgets/foldwidget.py
pynetix/widgets/sidebar.py
pynetix/widgets/splitter.py
pynetix/widgets/tabwidget.py
pynetix-0.1a0.dist-info/LICENSE
pynetix-0.1a0.dist-info/METADATA
pynetix-0.1a0.dist-info/WHEEL
pynetix-0.1a0.dist-info/top_level.txt
pynetix-0.1a0.dist-info/RECORD
