Metadata-Version: 2.1
Name: pynetix
Version: 0.1a0
Summary: Chemistry tool for fitting reaction kinetics data in the 96-well plate format.
Home-page: https://github.com/brands-d/ pynetix
Author: Dominik Brandstetter
Author-email: brandstetter.dominik@gmx.net
License: MIT
License-File: LICENSE
Requires-Dist: pyside6 (>=6.4.0)
Requires-Dist: numpy (>=1.23.4)
Requires-Dist: pyqtgraph (>=0.13.1)
